rust_python_jsonpatch-0.1.11.dist-info/METADATA
rust_python_jsonpatch-0.1.11.dist-info/WHEEL
rust_python_jsonpatch.libs/libgcc_s-60abea67.so.1
rust_python_jsonpatch/__init__.py
rust_python_jsonpatch/rust_python_jsonpatch.cpython-37m-aarch64-linux-gnu.so
rust_python_jsonpatch-0.1.11.dist-info/RECORD
