Metadata-Version: 2.3
Name: rust_python_jsonpatch
Version: 0.1.11
Classifier: Programming Language :: Python :: 3
Classifier: License :: OSI Approved :: MIT License
Classifier: Operating System :: OS Independent
Summary: Rust json path wrapper
Author-email: Koca <admin@koca.win>
License: MIT
Project-URL: repository, https://github.com/rockkoca/python_rust_json_patch
